README.md
setup.py
asgard/__init__.py
asgard/sdk/__init__.py
asgard/sdk/options/__init__.py
asgard_api_sdk.egg-info/PKG-INFO
asgard_api_sdk.egg-info/SOURCES.txt
asgard_api_sdk.egg-info/dependency_links.txt
asgard_api_sdk.egg-info/top_level.txt