Metadata-Version: 1.1
Name: asgard-api-sdk
Version: 0.1.0
Summary: Asgard API common code
Home-page: https://github.com/B2W-BIT/asgard-api-sdk
Author: Dalton Barreto
Author-email: daltonmatos@gmail.com
License: MIT
Platform: UNKNOWN
Classifier: Programming Language :: Python :: 3.6
